forgot_again/__init__.py
forgot_again/file.py
forgot_again/string.py
forgot_again-0.0.3.dist-info/LICENSE.txt
forgot_again-0.0.3.dist-info/METADATA
forgot_again-0.0.3.dist-info/WHEEL
forgot_again-0.0.3.dist-info/top_level.txt
forgot_again-0.0.3.dist-info/RECORD
